{
    "2022-03-18": [{
        "League": "Primeira Liga",
        "HomeTeam": "Vizela",
        "AwayTeam": "Famalicao",
        "Prediction": "2",
        "Odds": "2.82",
        "Win": "-1",
        "Book": "Pinnacle"
    }, {
        "League": "Eredivisie",
        "HomeTeam": "Heerenveen",
        "AwayTeam": "Heracles",
        "Prediction": "X",
        "Odds": "3.26",
        "Win": "-1",
        "Book": "Pinnacle"
    }],
    "2022-03-19": [{
        "League": "Scottish PL",
        "HomeTeam": "St Johnstone",
        "AwayTeam": "Motherwell",
        "Prediction": "X",
        "Odds": "3.05",
        "Win": "-1",
        "Book": "Pinnacle"
    }, {
        "League": "Belgian First",
        "HomeTeam": "Charleroi",
        "AwayTeam": "Cercle Brugge",
        "Prediction": "X",
        "Odds": "3.5",
        "Win": "-1",
        "Book": "Bet365"
    }, {
        "League": "Premier League",
        "HomeTeam": "Aston Villa",
        "AwayTeam": "Arsenal",
        "Prediction": "X",
        "Odds": "3.5",
        "Win": "-1",
        "Book": "Bet&Win"
    }, {
        "League": "La Liga",
        "HomeTeam": "Elche",
        "AwayTeam": "Valencia",
        "Prediction": "2",
        "Odds": "2.86",
        "Win": "-1",
        "Book": "Pinnacle"
    }, {
        "League": "La Liga",
        "HomeTeam": "Alaves",
        "AwayTeam": "Granada",
        "Prediction": "X",
        "Odds": "3.32",
        "Win": "-1",
        "Book": "Pinnacle"
    }],
    "2022-03-20": [{
        "League": "Belgian First",
        "HomeTeam": "Gent",
        "AwayTeam": "Anderlecht",
        "Prediction": "X",
        "Odds": "3.4",
        "Win": "-1",
        "Book": "Bet365"
    }, {
        "League": "Ligue 1",
        "HomeTeam": "Lorient",
        "AwayTeam": "Strasbourg",
        "Prediction": "X",
        "Odds": "3.4",
        "Win": "2.4",
        "Book": "Bet&Win"
    }, {
        "League": "Ligue 1",
        "HomeTeam": "Angers",
        "AwayTeam": "Brest",
        "Prediction": "X",
        "Odds": "3.3",
        "Win": "-1",
        "Book": "Interwetten"
    }, {
        "League": "Primeira Liga",
        "HomeTeam": "Pacos Ferreira",
        "AwayTeam": "Moreirense",
        "Prediction": "X",
        "Odds": "3.3",
        "Win": "-1",
        "Book": "Bet365"
    }, {
        "League": "Seria A",
        "HomeTeam": "Roma",
        "AwayTeam": "Lazio",
        "Prediction": "X",
        "Odds": "3.47",
        "Win": "-1",
        "Book": "Pinnacle"
    }, {
        "League": "La Liga",
        "HomeTeam": "Celta",
        "AwayTeam": "Betis",
        "Prediction": "2",
        "Odds": "3.45",
        "Win": "-1",
        "Book": "Pinnacle"
    }]
}